setup.py
ansible_inventory_creator/__init__.py
ansible_inventory_creator/main.py
ansible_inventory_creator/utils.py
ansible_inventory_creator/version.py
ansible_inventory_creator.egg-info/PKG-INFO
ansible_inventory_creator.egg-info/SOURCES.txt
ansible_inventory_creator.egg-info/dependency_links.txt
ansible_inventory_creator.egg-info/top_level.txt