Metadata-Version: 1.0
Name: ansible-inventory-creator
Version: 0.0.5
Summary: Python helper library to abstract out common work for creating ansible dynamic inventory scripts
Home-page: https://github.com/saurabh-hirani/ansible_inventory_creator
Author: Saurabh Hirani
Author-email: saurabh.hirani@gmail.com
License: MIT
Platform: UNKNOWN
